lib_cli_exit_tools/__init__.py
lib_cli_exit_tools/__init__conf__.py
lib_cli_exit_tools/__main__.py
lib_cli_exit_tools/cli.py
lib_cli_exit_tools/lib_cli_exit_tools.py
lib_cli_exit_tools/py.typed
lib_cli_exit_tools/adapters/__init__.py
lib_cli_exit_tools/adapters/signals.py
lib_cli_exit_tools/application/__init__.py
lib_cli_exit_tools/application/runner.py
lib_cli_exit_tools/core/__init__.py
lib_cli_exit_tools/core/configuration.py
lib_cli_exit_tools/core/exit_codes.py
lib_cli_exit_tools-2.2.2.dist-info/METADATA
lib_cli_exit_tools-2.2.2.dist-info/WHEEL
lib_cli_exit_tools-2.2.2.dist-info/entry_points.txt
lib_cli_exit_tools-2.2.2.dist-info/licenses/LICENSE
lib_cli_exit_tools-2.2.2.dist-info/RECORD
