Metadata-Version: 2.4
Name: lib_cli_exit_tools
Version: 2.2.2
Summary: CLI exit handling helpers: clean signals, exit codes, and error printing
Project-URL: Homepage, https://github.com/bitranox/lib_cli_exit_tools
Project-URL: Repository, https://github.com/bitranox/lib_cli_exit_tools.git
Project-URL: Issues, https://github.com/bitranox/lib_cli_exit_tools/issues
Author-email: bitranox <bitranox@gmail.com>
License: MIT
License-File: LICENSE
Keywords: cli,click,errors,exit,signals
Classifier: Environment :: Console
Classifier: License :: OSI Approved :: MIT License
Classifier: Operating System :: OS Independent
Classifier: Programming Language :: Python :: 3
Classifier: Programming Language :: Python :: 3 :: Only
Classifier: Typing :: Typed
Requires-Python: >=3.10
Requires-Dist: rich-click>=1.9.4
Provides-Extra: dev
Requires-Dist: bandit>=1.9.2; extra == 'dev'
Requires-Dist: build>=1.3.0; extra == 'dev'
Requires-Dist: codecov-cli>=11.2.6; extra == 'dev'
Requires-Dist: coverage[toml]>=7.13.0; extra == 'dev'
Requires-Dist: hypothesis>=6.148.7; extra == 'dev'
Requires-Dist: import-linter>=2.9; extra == 'dev'
Requires-Dist: pip-audit>=2.10.0; extra == 'dev'
Requires-Dist: pyright>=1.1.407; extra == 'dev'
Requires-Dist: pytest-asyncio>=1.3.0; extra == 'dev'
Requires-Dist: pytest-cov>=7.0.0; extra == 'dev'
Requires-Dist: pytest>=9.0.2; extra == 'dev'
Requires-Dist: rtoml>=0.13.0; extra == 'dev'
Requires-Dist: ruff>=0.14.9; extra == 'dev'
Requires-Dist: textual>=6.8.0; extra == 'dev'
Requires-Dist: twine>=6.2.0; extra == 'dev'
